vibeq/__init__.py
vibeq/__main__.py
vibeq/browser.py
vibeq/browser_playwright.py
vibeq/cli.py
vibeq/core.py
vibeq/multi_browser.py
vibeq/offline_intelligence.py
vibeq/pattern_learning.py
vibeq/performance_layer.py
vibeq/production_errors.py
vibeq/selector_cache.py
vibeq/selectors.py
vibeq/wait.py
vibeq/wait_strategies.py
vibeq/webdriver_compat.py
vibeq/core_modules/__init__.py
vibeq/core_modules/action_executor.py
vibeq/core_modules/command_parser.py
vibeq/core_modules/element_finder.py
vibeq/core_modules/engine.py
vibeq/core_modules/universal_element_finder.py
vibeq/demo/__init__.py
vibeq/demo/__main__.py
vibeq/examples/__init__.py
vibeq/examples/complete_ecommerce.py
vibeq/examples/quick_start.py
vibeq/providers/__init__.py
vibeq/providers/anthropic.py
vibeq/providers/factory.py
vibeq/providers/grok.py
vibeq/providers/local.py
vibeq/providers/openai.py
vibeq/providers/universal_ai.py
vibeq-1.0.1.dist-info/licenses/LICENSE
vibeq-1.0.1.dist-info/METADATA
vibeq-1.0.1.dist-info/WHEEL
vibeq-1.0.1.dist-info/entry_points.txt
vibeq-1.0.1.dist-info/top_level.txt
vibeq-1.0.1.dist-info/RECORD
