Metadata-Version: 2.4
Name: vibeq
Version: 1.0.1
Summary: Universal AI-native test automation that works on ANY website - no hardcoded selectors, self-healing, production-ready
Author-email: VibeQ Team <hello@vibeq.io>
License-Expression: MIT
Project-URL: Homepage, https://github.com/Ronaldozero7/vibeq
Project-URL: Repository, https://github.com/Ronaldozero7/vibeq
Project-URL: Documentation, https://github.com/Ronaldozero7/vibeq#readme
Project-URL: Issues, https://github.com/Ronaldozero7/vibeq/issues
Project-URL: Discussions, https://github.com/Ronaldozero7/vibeq/discussions
Keywords: testing,automation,selenium,playwright,webdriver,bidi,ai,self-healing
Classifier: Development Status :: 5 - Production/Stable
Classifier: Programming Language :: Python :: 3
Classifier: Programming Language :: Python :: 3.8
Classifier: Programming Language :: Python :: 3.9
Classifier: Programming Language :: Python :: 3.10
Classifier: Programming Language :: Python :: 3.11
Classifier: Programming Language :: Python :: 3.12
Classifier: Programming Language :: Python :: 3.13
Classifier: Operating System :: OS Independent
Classifier: Topic :: Software Development :: Testing
Classifier: Topic :: Software Development :: Quality Assurance
Classifier: Intended Audience :: Developers
Requires-Python: >=3.8
License-File: LICENSE
Requires-Dist: requests>=2.28
Requires-Dist: playwright>=1.40.0
Requires-Dist: openai>=1.0.0
Requires-Dist: anthropic>=0.25.0
Provides-Extra: dev
Requires-Dist: pytest; extra == "dev"
Requires-Dist: playwright; extra == "dev"
Requires-Dist: requests; extra == "dev"
Requires-Dist: mypy; extra == "dev"
Requires-Dist: ruff; extra == "dev"
Requires-Dist: flake8; extra == "dev"
Requires-Dist: coverage; extra == "dev"
Provides-Extra: all
Requires-Dist: playwright; extra == "all"
Requires-Dist: anthropic; extra == "all"
Requires-Dist: openai; extra == "all"
Dynamic: license-file
